Metadata-Version: 2.1
Name: ts-dataweave
Version: 1.0.3
Summary: Python wrapper around MuleSoft DataWeave data transformation engine.
Home-page: https://developers.tetrascience.com
Author: Ian Cooper
Author-email: icooper@tetrasience.com
License: UNKNOWN
Platform: UNKNOWN
Classifier: License :: OSI Approved :: Apache Software License
Classifier: Operating System :: MacOS :: MacOS X
Classifier: Operating System :: POSIX :: Linux
Classifier: Programming Language :: Python :: 3
Requires-Python: >=3.7
License-File: LICENSE.txt
